{
"而":"y, además; pero, sin embargo (conjunción)",
"却":"pero, sin embargo, no obstante",
"担心":"preocuparse, inquietarse; preocupado",
"之后":"después de, tras; luego, después",
"了解":"conocer, entender; enterarse de, informarse",
"无":"no tener; sin; no, nada",
"选择":"elegir, escoger; elección, opción",
"此":"este, esto; aquí",
"作为":"como, en calidad de; conducta, actuación; considerar como",
"呀":"(partícula exclamativa: ¡ah!, ¡oh!)",
"之间":"entre, en medio de",
"关于":"acerca de, sobre, respecto a",
"甚至":"incluso, hasta; tanto que",
"之前":"antes de, previo a; hace",
"无法":"no poder, ser incapaz de, no haber manera de",
"对于":"respecto a, en cuanto a, para",
"处":"estar en, encontrarse en; (chù) lugar; departamento",
"政府":"gobierno",
"曾":"alguna vez, en el pasado, ya (marcador de pasado)",
"系统":"sistema; sistemático",
"是否":"si (es o no), si acaso",
"以及":"así como, y, además de",
"自":"desde, de; uno mismo, auto-",
"研究":"investigar, estudiar; investigación, estudio",
"定":"fijar, establecer, determinar; seguro",
"考虑":"considerar, pensar, reflexionar; consideración",
"提供":"ofrecer, proporcionar, brindar, suministrar",
"首":"(clasificador de canciones y poemas); cabeza; primero; jefe",
"治疗":"tratar (una enfermedad); tratamiento, terapia",
"根据":"según, de acuerdo con; base, fundamento",
"获得":"obtener, conseguir, ganar, recibir",
"法":"ley, derecho; método; Francia (abrev.)",
"局":"oficina, buró; situación; partida (de un juego)",
"未来":"futuro, porvenir; venidero",
"看来":"al parecer, por lo visto, parece que",
"严重":"grave, serio, severo",
"包括":"incluir, abarcar, comprender",
"法律":"ley, derecho; jurídico",
"项":"(clasificador de proyectos, tareas, cláusulas); nuca",
"底":"fondo, base; final (de un periodo)",
"不管":"sin importar, no importa; no ocuparse de",
"解释":"explicar, aclarar; explicación; interpretar",
"历史":"historia; histórico",
"之一":"uno de (los...)",
"项目":"proyecto; rubro, partida; prueba (deportiva)",
"梦":"sueño; soñar",
"单":"solo, único; impar; lista, formulario; sencillo",
"非":"no ser; no-, in- (prefijo negativo); África (abrev.)",
"总统":"presidente (de un país)",
"似乎":"parecer, aparentemente, como si",
"应":"deber; aceptar, responder; (yìng) responder a",
"几乎":"casi, prácticamente, por poco",
"宝贝":"tesoro; cariño, bebé, cielo",
"位置":"posición, ubicación, lugar; puesto",
"方":"lado, parte; cuadrado; método; dirección",
"附近":"cerca, cercanías, alrededores; cercano",
"参与":"participar en, tomar parte en, intervenir",
"而是":"sino (que)",
"王":"rey, monarca; Wang (apellido)",
"手术":"cirugía, operación (quirúrgica)",
"加入":"unirse a, afiliarse a, ingresar en; añadir",
"兄弟":"hermanos; hermano menor",
"遇到":"encontrarse con, toparse con, enfrentar",
"轮":"rueda; turno, ronda; turnarse; (clasificador de rondas)",
"地址":"dirección, domicilio",
"无论":"sin importar, no importa (qué, cómo), cualquiera que sea",
"投":"lanzar, arrojar, tirar; invertir; enviar",
"资料":"datos, información, material, documentación",
"于是":"entonces, por consiguiente, así que",
"心理":"psicología; mentalidad; psicológico",
"根":"raíz; base, origen; (clasificador de objetos largos y delgados)",
"停下":"detenerse, parar",
"妻子":"esposa, mujer",
"亲爱":"querido, amado",
"引起":"provocar, causar, suscitar, despertar",
"共":"en total; común; juntos, compartir",
"或许":"quizá, tal vez, acaso",
"投资":"invertir; inversión",
"抱":"abrazar; cargar (en brazos); abrigar (esperanzas)",
"律师":"abogado",
"导致":"provocar, ocasionar, conducir a",
"战争":"guerra",
"机构":"organismo, institución, agencia; mecanismo",
"反":"contrario, inverso; anti-; oponerse; al revés",
"伤害":"dañar, herir, lastimar; daño",
"空间":"espacio; margen",
"冲":"embestir, precipitarse; enjuagar; preparar (con agua)",
"期待":"esperar (con ilusión), aguardar; expectativa",
"政治":"política; político",
"承认":"admitir, reconocer, aceptar",
"怪":"raro, extraño; culpar; monstruo; bastante",
"型":"tipo, modelo; molde",
"传统":"tradición; tradicional",
"盘":"plato, bandeja; disco; (clasificador de partidas); enrollar",
"丈夫":"esposo, marido",
"翻":"voltear, dar la vuelta; hojear, rebuscar; traducir",
"竟然":"inesperadamente, para sorpresa de uno, ¡y encima!",
"的确":"realmente, en efecto, efectivamente",
"倍":"vez, veces (multiplicador); doble",
"醒":"despertar(se); estar despierto; espabilarse",
"身份":"identidad; condición, calidad (de)",
"极":"extremadamente, sumamente; polo; extremo",
"否则":"de lo contrario, si no, o bien",
"免费":"gratis, gratuito, sin costo",
"牌":"letrero, placa; marca; carta, ficha (de juego)",
"俩":"dos, los dos, ambos (coloquial)",
"产品":"producto, artículo, mercancía",
"测试":"probar, testear; prueba, test, examen",
"落":"caer; quedarse atrás; olvidar (algo en un lugar)",
"著名":"famoso, célebre, renombrado",
"寻找":"buscar, ir en busca de",
"梦想":"sueño, anhelo; soñar con",
"帅":"guapo, apuesto; elegante; comandante",
"网络":"red; internet",
"烧":"quemar; cocinar, guisar; tener fiebre",
"数据":"datos, cifras",
"申请":"solicitar, pedir; solicitud",
"安":"tranquilo, en paz; instalar; seguridad",
"圈":"círculo, aro; ámbito, círculo (social); encerrar",
"稳定":"estable, firme; estabilidad; estabilizar",
"巨大":"enorme, gigantesco, inmenso",
"土地":"tierra, terreno, suelo; territorio",
"老婆":"esposa, mujer (coloquial)",
"挑战":"desafiar, retar; desafío, reto",
"秘密":"secreto; secreto, confidencial",
"季":"estación (del año); temporada",
"失败":"fracasar, perder; fracaso, derrota",
"抽":"sacar, extraer; fumar; azotar; sortear",
"想象":"imaginar; imaginación",
"教授":"profesor, catedrático; enseñar",
"吸引":"atraer, cautivar, fascinar",
"顶":"cima, cumbre; techo; (clasificador de sombreros); sumamente",
"既然":"ya que, puesto que, dado que",
"货":"mercancía, producto, género",
"特殊":"especial, particular, singular",
"提醒":"recordar (a alguien), advertir, avisar",
"风格":"estilo",
"角色":"papel, rol, personaje",
"彻底":"a fondo, completamente; total, radical",
"投入":"dedicarse a, entregarse a; invertir; entregado",
"优秀":"excelente, sobresaliente, destacado",
"儿童":"niño, infante; infantil",
"权利":"derecho (jurídico)",
"既":"ya que; tanto... (como...); ya",
"期间":"periodo, durante, lapso",
"手里":"en la mano, en manos de",
"距离":"distancia; distar de, estar a",
"轻松":"relajado, tranquilo; ligero, fácil; relajarse",
"敌人":"enemigo",
"程序":"programa (informático); procedimiento, trámite",
"医疗":"atención médica, tratamiento médico; sanitario",
"毕业":"graduarse, titularse; graduación",
"切":"cortar, rebanar; (qiè) ajustarse a; no... en absoluto",
"怀疑":"dudar de, sospechar; duda, sospecha",
"合同":"contrato",
"处于":"estar en, encontrarse en (un estado o situación)",
"垃圾":"basura, desechos; (fig.) porquería",
"戴":"ponerse, llevar (gafas, sombrero, guantes)",
"究竟":"al fin y al cabo; en definitiva; ¿qué exactamente...?",
"然而":"sin embargo, no obstante, pero",
"赢得":"ganar(se), obtener, conquistar",
"战斗":"combatir, luchar; combate, batalla",
"官":"funcionario, oficial; órgano",
"替":"por, en lugar de; sustituir, reemplazar",
"兴奋":"emocionado, entusiasmado; emoción, excitación",
"兴趣":"interés, afición",
"人家":"otros, los demás; familia, hogar; (coloquial) uno",
"摆":"colocar, poner; exhibir; menear; péndulo",
"立即":"inmediatamente, de inmediato, en el acto",
"色":"color; expresión; tipo; sensualidad",
"内部":"interior, interno, dentro (de una organización)",
"在于":"consistir en, radicar en, depender de",
"发挥":"desplegar, poner en juego (capacidades); desarrollar",
"符合":"concordar con, ajustarse a, cumplir con",
"编":"redactar, compilar; tejer, trenzar; inventar (historias)",
"独立":"independiente; independencia; independizarse",
"表情":"expresión (facial), gesto; emoticono",
"躺":"acostarse, tumbarse, recostarse",
"采访":"entrevistar; entrevista, reportaje",
"针对":"dirigirse a, enfocarse en; en respuesta a; contra",
"即将":"estar a punto de, próximamente, en breve",
"宝":"tesoro, joya; precioso",
"答案":"respuesta, solución",
"规则":"regla, norma, reglamento; regular",
"激动":"emocionarse; emocionado, conmovido; emocionante",
"依然":"todavía, aún, como antes",
"阶段":"etapa, fase, estadio",
"擦":"frotar, limpiar; secar(se); aplicar (crema); rozar",
"无聊":"aburrido; sin sentido, insulso",
"一致":"unánime; coherente, consistente; de acuerdo",
"宝宝":"bebé, nene; tesoro (apelativo cariñoso)",
"刺激":"estimular; provocar, irritar; estímulo; emocionante",
"贴":"pegar, adherir; publicar (en línea); pegado a",
"显著":"notable, destacado, significativo",
"美女":"mujer hermosa, belleza, guapa",
"尽快":"cuanto antes, lo más pronto posible",
"药物":"medicamento, fármaco",
"移动":"mover(se), desplazar(se); móvil",
"销售":"vender, comercializar; venta(s)",
"呼吸":"respirar; respiración",
"确认":"confirmar, verificar; confirmación",
"出色":"sobresaliente, destacado, brillante",
"冰":"hielo; helado, frío; enfriar",
"结":"nudo; atar, anudar; (jiē) dar fruto",
"材料":"material; datos, documentación; madera (fig., persona)",
"转移":"trasladar, transferir; desviar (la atención)",
"烦":"molesto, fastidiado; molestar; hastiado",
"付出":"pagar; entregar, dedicar (esfuerzo, tiempo)",
"卷":"rollo; enrollar; (juàn) examen; tomo, volumen",
"透":"penetrar, traspasar; filtrar; completamente",
"治":"gobernar; curar, tratar; controlar (aguas)",
"措施":"medida, disposición",
"失望":"decepcionado, desilusionado; perder la esperanza",
"号码":"número",
"利益":"interés, beneficio, provecho",
"方案":"plan, propuesta, proyecto, esquema",
"主题":"tema, asunto central; temático",
"避免":"evitar, eludir, prevenir",
"量":"cantidad, volumen; (liáng) medir",
"女士":"señora, dama",
"闹":"armar alboroto; ruidoso; hacer (una escena); sufrir de",
"系列":"serie, colección, gama",
"盖":"tapa, cubierta; tapar, cubrir; construir",
"原则":"principio, norma",
"检测":"detectar, examinar; detección, análisis",
"奖":"premio, galardón; premiar",
"微笑":"sonreír; sonrisa",
"列":"fila, columna; enumerar, alinear; (clasificador de trenes)",
"良好":"bueno, favorable, satisfactorio",
"思考":"reflexionar, meditar, pensar; reflexión",
"夫人":"señora, esposa (de alguien), dama",
"户":"hogar, familia (unidad); puerta; cuenta",
"归":"volver, regresar; devolver; pertenecer a",
"严格":"estricto, riguroso, severo",
"不然":"de lo contrario, si no; no es así",
"企业":"empresa, compañía, negocio",
"追求":"perseguir (una meta); aspirar a; cortejar",
"脱":"quitarse (ropa); desprenderse; escapar de",
"挑":"elegir, escoger; cargar al hombro; (tiǎo) provocar",
"放松":"relajar(se), aflojar, soltar",
"阻止":"impedir, detener, frenar",
"老公":"esposo, marido (coloquial)",
"资源":"recurso(s)",
"主席":"presidente (de una organización, asamblea)",
"苦":"amargo; sufrimiento, penuria; sufrir; arduamente",
"吸":"aspirar, inhalar; absorber; fumar",
"箱":"caja, baúl, maleta",
"行业":"sector, industria, ramo, gremio",
"士兵":"soldado",
"承担":"asumir, cargar con, hacerse responsable de",
"面临":"enfrentar, afrontar, estar ante",
"神秘":"misterioso; misterio",
"登记":"registrarse, inscribirse; registro",
"下降":"descender, bajar, disminuir",
"来源":"fuente, origen, procedencia; provenir de",
"充分":"suficiente, pleno; plenamente, a fondo",
"批":"lote, tanda; (clasificador de lotes, grupos); criticar; aprobar",
"经典":"clásico; los clásicos; clásico (obra)",
"法院":"tribunal, juzgado, corte",
"背景":"fondo; contexto, antecedentes; padrino (fig.)",
"大会":"asamblea, congreso, gran reunión",
"减少":"reducir, disminuir, aminorar",
"恶心":"náuseas, asco; asqueroso, repugnante",
"兵":"soldado; tropas; arma",
"回复":"responder, contestar; restablecerse; respuesta",
"居民":"residente, habitante, vecino",
"限制":"limitar, restringir; límite, restricción",
"万一":"por si acaso, en caso de que; imprevisto",
"如今":"hoy en día, actualmente, ahora",
"分手":"romper, terminar (una relación); separarse",
"牙":"diente, muela; marfil",
"细节":"detalle, pormenor",
"维持":"mantener, sostener, conservar",
"迅速":"rápido, veloz; rápidamente",
"有趣":"interesante, divertido, entretenido",
"似的":"como, parecido a, como si",
"出席":"asistir a, estar presente en",
"婚礼":"boda, ceremonia nupcial",
"财产":"propiedad, bienes, patrimonio",
"刺":"espina; picar, pinchar; apuñalar",
"工程":"ingeniería; obra, proyecto (de construcción)",
"肥":"gordo; fértil; holgado; fertilizante",
"镜头":"lente, objetivo; toma, escena (cine)",
"实施":"implementar, aplicar, poner en práctica",
"湿":"mojado, húmedo",
"暗":"oscuro; secreto, oculto; a escondidas",
"诗":"poema, poesía, verso",
"类型":"tipo, clase, categoría",
"自信":"confianza en sí mismo; seguro de sí, con autoestima",
"守":"vigilar, custodiar; defender; cumplir (normas)",
"操作":"operar, manejar; operación, manejo",
"新鲜":"fresco; novedoso, original",
"标志":"señal, símbolo, logotipo; marcar, señalar",
"黄金":"oro; dorado, de oro (época, horario)",
"获":"obtener, ganar, lograr; capturar",
"指挥":"dirigir, comandar; director (de orquesta); mando",
"伙伴":"compañero, socio, pareja (de actividad)",
"摸":"tocar, palpar; acariciar; tantear",
"法官":"juez",
"脑袋":"cabeza; sesos, cerebro",
"祝福":"bendecir, desear lo mejor; bendición, buenos deseos",
"承受":"soportar, aguantar, resistir; heredar",
"肚子":"barriga, vientre, estómago",
"松":"suelto, flojo; aflojar, soltar; pino; relajado",
"地位":"posición, estatus, rango, lugar",
"登":"subir, escalar; publicar; registrar",
"结构":"estructura, composición, construcción",
"辣":"picante, picoso; picar",
"质量":"calidad; masa (física)",
"在乎":"importarle a uno, preocuparse por",
"遇":"encontrarse con; trato; ocasión",
"寄":"enviar (por correo), mandar; confiar a",
"造型":"diseño, estilo, look, figura; modelar",
"引":"guiar, conducir; atraer; citar",
"降":"bajar, descender; caer; reducir",
"禁止":"prohibir, vedar",
"圆":"círculo; redondo, circular; esfera",
"睡着":"quedarse dormido, conciliar el sueño",
"度过":"pasar (tiempo), atravesar, superar (una etapa)",
"地下":"subterráneo; bajo tierra; clandestino",
"冷静":"tranquilo, sereno, con la cabeza fría; calmarse",
"闪":"destellar, relampaguear; esquivar; aparecer fugazmente",
"袋":"bolsa, saco, costal; bolsillo",
"购物":"hacer compras, comprar; compras",
"勇敢":"valiente, valeroso, audaz",
"散":"dispersarse, disolverse; suelto; esparcir",
"依靠":"apoyarse en, depender de; respaldo, sostén",
"弱":"débil, flojo; inferior",
"购买":"comprar, adquirir",
"战士":"soldado, combatiente, guerrero",
"针":"aguja; inyección; puntada",
"装置":"dispositivo, aparato, instalación; instalar",
"划":"remar; (huà) trazar, delimitar; planear; valer la pena",
"移":"mover, trasladar, desplazar; cambiar",
"测":"medir, sondear; conjeturar",
"巧克力":"chocolate",
"临时":"temporal, provisional; a última hora",
"单独":"solo, a solas, por separado, individual",
"医学":"medicina (ciencia); médico (adj.)",
"大型":"de gran tamaño, a gran escala, grande",
"降低":"reducir, bajar, disminuir",
"刷":"cepillar; pintar (con brocha); deslizar (tarjeta); cepillo",
"作出":"tomar (una decisión), hacer (una propuesta), emitir",
"酒吧":"bar, cantina, pub",
"激烈":"intenso, feroz, reñido, acalorado",
"想念":"extrañar, echar de menos, añorar",
"预测":"pronosticar, predecir; pronóstico, predicción",
"固定":"fijo, estable; fijar, sujetar",
"勇气":"valor, valentía, coraje",
"位于":"estar ubicado en, situarse en, encontrarse en",
"摇":"sacudir, agitar, mecer; negar (con la cabeza)",
"密码":"contraseña, clave, código secreto",
"培养":"formar, cultivar, educar; cultivo",
"平静":"tranquilo, sereno, en calma; calmarse",
"维护":"defender, salvaguardar, proteger; mantener",
"无数":"innumerables, incontables, infinidad de",
"对付":"lidiar con, hacer frente a; arreglárselas",
"关闭":"cerrar; apagar; clausurar",
"运动员":"atleta, deportista",
"姐妹":"hermanas; hermana",
"航空":"aviación; aéreo",
"外套":"abrigo, chaqueta, chamarra",
"聚会":"reunión, fiesta, encuentro; reunirse",
"交换":"intercambiar, canjear; intercambio",
"描述":"describir; descripción",
"聚":"reunirse, juntarse, congregarse",
"黑暗":"oscuridad, tinieblas; oscuro, tenebroso",
"运气":"suerte, fortuna",
"设置":"configurar, establecer; instalar; configuración",
"含":"contener; tener en la boca; encerrar (un sentido)",
"典型":"típico; modelo, ejemplo clásico, arquetipo",
"夫妇":"matrimonio, pareja, marido y mujer",
"教训":"lección, escarmiento; sermonear, reprender",
"结论":"conclusión, veredicto",
"清醒":"lúcido, despejado, sobrio; despertarse; darse cuenta",
"总之":"en resumen, en fin, en una palabra",
"地面":"suelo, piso; superficie terrestre",
"纯":"puro; simple, mero; genuino",
"稳":"estable, firme, seguro",
"统一":"unificar, unir; unificado, unitario; unificación",
"玉米":"maíz, elote",
"身材":"figura, cuerpo, complexión, talle",
"设施":"instalaciones, infraestructura, equipamiento",
"腰":"cintura; espalda baja, lumbar",
"义务":"obligación, deber; voluntario, gratuito",
"运用":"emplear, aplicar, hacer uso de",
"逐渐":"gradualmente, poco a poco, progresivamente",
"酸":"ácido, agrio; adolorido; (fig.) dolido, envidioso",
"沉默":"silencio; callado, taciturno; guardar silencio",
"独特":"único, singular, peculiar, distintivo",
"遇见":"encontrarse con, toparse con",
"折":"doblar; romper(se); descuento; (zhé) plegar",
"摆脱":"librarse de, deshacerse de, zafarse de",
"夫妻":"matrimonio, esposos, marido y mujer",
"财富":"riqueza, fortuna, patrimonio",
"眼泪":"lágrimas",
"模型":"modelo, maqueta; molde",
"精力":"energía, vigor, fuerzas",
"隔":"separar; estar a (una distancia); cada (intervalo)",
"宽":"ancho, amplio; holgado; indulgente",
"统计":"estadística; contabilizar, sumar",
"特征":"característica, rasgo distintivo",
"叔叔":"tío (hermano menor del padre); señor (trato infantil)",
"平均":"promedio, media; en promedio; equitativo",
"县":"condado, distrito (división administrativa)",
"供应":"suministrar, abastecer, proveer; suministro",
"事物":"cosa, objeto, asunto",
"相反":"contrario, opuesto; al contrario, al revés",
"演讲":"discurso, conferencia; dar un discurso",
"帽子":"sombrero, gorra, gorro; etiqueta (fig.)",
"负担":"carga, peso; cargar con, costear",
"战胜":"vencer, derrotar, superar",
"过分":"excesivo, exagerado; pasarse de la raya",
"密":"denso, tupido; secreto; estrecho (relación)",
"反而":"al contrario, en cambio, en vez de eso",
"街道":"calle; barrio (unidad administrativa)",
"培训":"capacitar, formar; capacitación, formación",
"独自":"solo, a solas, por sí solo",
"扩大":"ampliar, expandir, agrandar",
"大哥":"hermano mayor; jefe (de banda); amigo (trato)",
"此外":"además, aparte de esto, por otra parte",
"奖金":"bono, prima, premio (en dinero)",
"盐":"sal",
"大众":"las masas, el público, popular",
"迟到":"llegar tarde, retrasarse",
"怀念":"añorar, recordar con cariño, extrañar",
"假如":"si, en caso de que, suponiendo que",
"改善":"mejorar; mejora",
"晒":"asolear, tomar el sol; secar al sol; (fig.) presumir (en línea)",
"减":"restar; reducir, disminuir",
"官方":"oficial (del gobierno)",
"引导":"guiar, conducir, orientar",
"航班":"vuelo (programado)",
"约会":"cita; quedar con alguien",
"末":"final, fin, último; extremo",
"形势":"situación, coyuntura, panorama",
"细":"fino, delgado; minucioso, detallado",
"受不了":"no aguantar, ser insoportable",
"出售":"vender, poner a la venta",
"厚":"grueso; profundo; generoso",
"锻炼":"hacer ejercicio, ejercitarse; templar, forjar",
"堵":"tapar, obstruir; atascado; agobiado",
"护士":"enfermero, enfermera",
"拍照":"tomar fotos, fotografiar",
"笨":"tonto, torpe, lento",
"收获":"cosecha; ganancia, fruto; cosechar",
"轻易":"fácilmente, a la ligera",
"大楼":"edificio (grande)",
"技巧":"técnica, destreza, habilidad",
"大陆":"continente; China continental",
"名人":"celebridad, persona famosa, personaje",
"各个":"cada uno, cada; uno por uno",
"电梯":"ascensor, elevador; escalera mecánica",
"抓紧":"aferrarse a; aprovechar bien; no perder tiempo en",
"相处":"convivir, llevarse (bien o mal), tratarse",
"反映":"reflejar; informar, transmitir (opiniones)",
"植物":"planta, vegetal; vegetación",
"阵":"ráfaga, racha; (clasificador de ráfagas, episodios); formación",
"转身":"darse la vuelta, girarse",
"从此":"desde entonces, a partir de ahí",
"矮":"bajo, chaparro; de poca altura",
"投诉":"quejarse, reclamar; queja, reclamación",
"减肥":"adelgazar, bajar de peso, hacer dieta",
"眼镜":"gafas, lentes, anteojos",
"体重":"peso (corporal)",
"面试":"entrevista (de trabajo); entrevistar",
"无所谓":"dar igual, no importar; indiferente",
"居住":"residir, vivir, habitar",
"翻译":"traducir, interpretar; traducción; traductor",
"移民":"emigrar, inmigrar; migrante, inmigrante; migración",
"担任":"desempeñar (un cargo), ocupar el puesto de, fungir como",
"风景":"paisaje, vista, panorama",
"沉":"hundirse; pesado; profundo (sueño); sumirse",
"善良":"bondadoso, bueno, de buen corazón",
"其余":"el resto, los demás, lo restante",
"规模":"escala, envergadura, magnitud",
"哪怕":"aunque, incluso si, así sea",
"伙":"grupo, banda; compañero; (clasificador de grupos)",
"最初":"al principio, inicialmente; primero, inicial",
"薄":"delgado, fino; débil; indiferente",
"窗户":"ventana",
"装修":"remodelar, decorar (un interior); remodelación",
"填":"rellenar, llenar (un formulario, un hueco)",
"召开":"convocar, celebrar (una reunión)",
"唱片":"disco (musical), álbum",
"有限":"limitado, finito",
"代替":"sustituir, reemplazar, suplir",
"冰箱":"refrigerador, nevera, frigorífico",
"汇报":"informar, rendir cuentas; informe",
"论文":"tesis, artículo académico, ensayo",
"眼里":"en los ojos de, a ojos de",
"不在乎":"no importarle a uno, traerle sin cuidado",
"棵":"(clasificador de árboles y plantas)",
"粗":"grueso; tosco, burdo; áspero; descuidado",
"综合":"integral, global; sintetizar, integrar",
"多年":"muchos años, de muchos años",
"形容":"describir, calificar",
"青春":"juventud; juvenil",
"列车":"tren",
"喜爱":"gustar de, apreciar, ser aficionado a; favorito",
"吸收":"absorber, asimilar; admitir, reclutar",
"败":"perder, ser derrotado; fracasar; derrotar",
"小伙子":"muchacho, chico, joven",
"舒适":"cómodo, confortable, acogedor",
"会计":"contador, contable; contabilidad",
"好友":"buen amigo, amigo cercano; contacto (en redes)",
"尺":"regla (instrumento); chi (un tercio de metro)",
"胖子":"gordo, persona gorda",
"阅读":"leer; lectura",
"阿姨":"tía (materna); señora; niñera",
"穷":"pobre; agotar; a fondo",
"奋斗":"luchar, esforzarse; lucha, esfuerzo",
"乐趣":"placer, gusto, deleite, diversión",
"多次":"muchas veces, repetidamente, en varias ocasiones",
"男女":"hombres y mujeres",
"收回":"recuperar, retirar; retractarse de",
"渐渐":"gradualmente, poco a poco",
"亲密":"íntimo, cercano, estrecho",
"着急":"preocuparse, angustiarse; tener prisa; ansioso",
"具备":"poseer, contar con, reunir (requisitos)",
"尽力":"esforzarse al máximo, hacer todo lo posible",
"新娘":"novia (en la boda)",
"下载":"descargar (archivos)",
"维修":"mantener, reparar; mantenimiento",
"构成":"constituir, formar, componer",
"口袋":"bolsillo; bolsa, saco",
"无限":"ilimitado, infinito, sin límites",
"吃惊":"sorprenderse, asombrarse, espantarse",
"嘴巴":"boca",
"扫":"barrer; escanear; pasar (la vista)",
"秘书":"secretario, secretaria",
"含量":"contenido (de una sustancia), proporción",
"燃烧":"arder, quemarse; combustión",
"极其":"extremadamente, sumamente, en extremo",
"日记":"diario (personal)",
"高潮":"clímax, punto culminante; marea alta",
"同情":"compadecer, simpatizar con; compasión, lástima",
"破产":"quebrar, arruinarse; quiebra, bancarrota",
"说不定":"quizá, tal vez, quién sabe, a lo mejor",
"挑选":"elegir, seleccionar, escoger",
"逛":"pasear, callejear, recorrer (tiendas)",
"单纯":"simple, ingenuo, puro; meramente",
"季节":"estación (del año), temporada",
"布置":"disponer, arreglar, decorar; asignar (tareas)",
"灯光":"iluminación, luces, luz",
"色彩":"color, colorido; matiz, tinte",
"健身":"hacer ejercicio, mantenerse en forma; fitness",
"事先":"de antemano, previamente, con antelación",
"失业":"quedarse sin trabajo, estar desempleado; desempleo",
"规律":"ley, regularidad, patrón; regular, ordenado",
"待遇":"trato; remuneración, condiciones (laborales)",
"比分":"marcador, puntuación (de un partido)",
"淡":"insípido, soso; ligero, suave; pálido; indiferente",
"江":"río (grande)",
"办事":"hacer gestiones, tramitar, trabajar",
"塑料":"plástico",
"做梦":"soñar; (fig.) ilusionarse en vano",
"分散":"dispersar(se), repartir; distraer(se)",
"器官":"órgano (del cuerpo)",
"前途":"porvenir, futuro, perspectivas",
"被迫":"verse obligado a, ser forzado a",
"误会":"malentendido; malinterpretar, entender mal",
"说服":"persuadir, convencer",
"台上":"en el escenario, sobre la tarima",
"保守":"conservador; guardar (un secreto)",
"获取":"obtener, conseguir, adquirir",
"暗示":"insinuar, dar a entender; indirecta, insinuación",
"成人":"adulto",
"汽油":"gasolina",
"浓":"concentrado, espeso, denso; intenso, fuerte",
"担保":"garantizar, avalar; garantía, aval",
"弯":"curva; doblado; doblar(se); agacharse",
"镜子":"espejo",
"忽视":"ignorar, pasar por alto, descuidar, desatender",
"密切":"estrecho, cercano; estrechamente; de cerca",
"招呼":"saludar; llamar; atender; avisar",
"小型":"pequeño, de pequeño tamaño, en miniatura",
"胸部":"pecho, tórax; busto",
"录取":"admitir (a un alumno), aceptar (a un candidato)",
"浅":"poco profundo, superficial; claro (color); somero",
"力气":"fuerza (física), energía",
"楼梯":"escalera(s)",
"老实":"honrado, sincero; obediente; ingenuo",
"品质":"calidad; cualidades, carácter",
"效率":"eficiencia, rendimiento",
"情景":"escena, situación, circunstancias",
"遗产":"herencia, legado, patrimonio",
"业余":"aficionado, amateur; tiempo libre, extralaboral",
"没错":"así es, correcto, sin duda, no hay error",
"身高":"estatura, altura (de una persona)",
"对比":"contrastar, comparar; contraste, comparación",
"季度":"trimestre",
"争论":"discutir, debatir, polemizar; discusión, polémica",
"保密":"guardar el secreto, mantener confidencial",
"赞助":"patrocinar, auspiciar; patrocinio",
"玉":"jade",
"打败":"derrotar, vencer; ser derrotado",
"缩小":"reducir(se), encoger(se), achicar",
"含有":"contener, incluir, llevar",
"抽烟":"fumar",
"收益":"ganancia, beneficio, rendimiento",
"潮":"marea; húmedo; moda, tendencia; moderno",
"拉开":"abrir (jalando); descorrer; distanciar, ampliar (diferencia)",
"大规模":"a gran escala, masivo, extenso",
"赞成":"estar a favor, aprobar, apoyar",
"复制":"copiar, duplicar, reproducir",
"消化":"digerir; digestión; asimilar",
"疑问":"duda, interrogante, pregunta",
"包裹":"paquete, bulto; envolver",
"善于":"ser bueno para, tener facilidad para, dominar",
"著作":"obra, escrito, libro (de autor)",
"大多":"en su mayoría, mayormente, casi todos",
"包含":"contener, incluir, encerrar",
"诚实":"honesto, honrado, sincero",
"毛衣":"suéter, jersey (de lana)",
"男士":"caballero, hombre, señor",
"总理":"primer ministro, premier",
"骨头":"hueso; carácter, temple (fig.)",
"上门":"ir a domicilio; visitar; cerrar la puerta",
"集合":"reunir(se), concentrarse; conjunto (matemáticas)",
"宝贵":"valioso, precioso, preciado",
"童年":"infancia, niñez",
"进口":"importar; importación; entrada",
"沉重":"pesado; grave; apesadumbrado",
"市区":"zona urbana, centro de la ciudad",
"封闭":"cerrar, sellar, clausurar; cerrado, hermético",
"遗传":"herencia (genética); heredar (rasgos); hereditario",
"孙子":"nieto (hijo del hijo)",
"期限":"plazo, fecha límite, término",
"参考":"consultar, tomar como referencia; referencia",
"泪":"lágrima",
"重量":"peso",
"缓解":"aliviar, mitigar, atenuar; distenderse",
"测量":"medir; medición",
"汇":"girar (dinero), remesar; confluir; recopilar",
"来不及":"no dar tiempo, ya ser tarde para",
"商务":"negocios, comercio; comercial",
"天真":"ingenuo, inocente, cándido",
"燃料":"combustible",
"发烧":"tener fiebre",
"替代":"sustituir, reemplazar; alternativo",
"安置":"acomodar, ubicar, colocar; asentar (a alguien)",
"美金":"dólar estadounidense",
"箱子":"caja, maleta, baúl",
"严":"estricto, severo; hermético",
"了不起":"extraordinario, impresionante, admirable",
"修理":"reparar, arreglar, componer",
"尺寸":"medidas, dimensiones, talla, tamaño",
"幼儿园":"jardín de niños, kínder, guardería",
"穿上":"ponerse (ropa)",
"吸烟":"fumar",
"影子":"sombra; reflejo; rastro, indicio",
"延长":"prolongar, alargar, extender",
"加班":"trabajar horas extra, quedarse a trabajar tarde",
"征服":"conquistar, someter; cautivar",
"途中":"en el camino, durante el trayecto",
"数码":"digital; número, cifra",
"延续":"continuar, prolongarse, perdurar",
"性质":"naturaleza, carácter, índole",
"电源":"fuente de energía, toma de corriente, alimentación",
"考察":"inspeccionar, estudiar (sobre el terreno); expedición",
"神话":"mito, mitología; leyenda",
"鲜":"fresco; vivo (color); sabroso; poco frecuente",
"避":"evitar, esquivar; refugiarse de",
"热闹":"animado, bullicioso, concurrido; animación",
"机遇":"oportunidad, ocasión, coyuntura favorable",
"伞":"paraguas, sombrilla",
"营业":"operar, estar abierto (un negocio); actividad comercial",
"含义":"significado, sentido, connotación",
"问候":"saludar, mandar saludos; saludo",
"紧密":"estrecho, íntimo (vínculo); estrechamente",
"诗人":"poeta",
"顺序":"orden, secuencia; por turno",
"瓜":"melón, calabaza, sandía (genérico de cucurbitáceas)",
"语音":"pronunciación, sonido del habla; de voz (mensaje)",
"图案":"diseño, motivo, patrón (decorativo)",
"准时":"puntual; a tiempo, a la hora",
"纪律":"disciplina",
"闪电":"relámpago, rayo",
"打扫":"limpiar, barrer, asear",
"上个月":"el mes pasado",
"童话":"cuento de hadas, cuento infantil",
"得意":"orgulloso, satisfecho de sí mismo, ufano",
"手套":"guantes, manoplas",
"记载":"registrar, dejar constancia; registro, crónica",
"毕业生":"graduado, egresado",
"总共":"en total, en conjunto",
"帅哥":"chico guapo, galán",
"粮食":"cereales, granos, alimentos (básicos)",
"豆腐":"tofu, queso de soya",
"推迟":"posponer, aplazar, retrasar",
"老家":"pueblo natal, tierra natal, casa paterna",
"促进":"promover, impulsar, fomentar",
"字母":"letra (del alfabeto)",
"个别":"individual, aislado; uno que otro, contados",
"利息":"interés (bancario)",
"潮流":"tendencia, corriente, moda",
"预订":"reservar, hacer una reservación; encargar",
"袜子":"calcetines, medias",
"推销":"promocionar, vender, comercializar",
"毛巾":"toalla",
"趋势":"tendencia, rumbo, curso",
"学术":"académico, científico; erudición",
"原料":"materia prima, insumo",
"透明":"transparente; transparencia",
"阳台":"balcón, terraza",
"抄":"copiar; plagiar; transcribir",
"寒冷":"frío, gélido, helado",
"鲜花":"flores (frescas)",
"名片":"tarjeta de presentación, tarjeta de visita",
"冬季":"invierno, temporada invernal",
"智力":"inteligencia, intelecto",
"降落":"aterrizar; descender",
"尾巴":"cola, rabo",
"智能":"inteligente (dispositivo); inteligencia",
"手工":"manual, hecho a mano; trabajo manual",
"来得及":"dar tiempo, llegar a tiempo, alcanzar",
"登录":"iniciar sesión, ingresar; registrarse",
"穷人":"pobre, los pobres",
"符号":"símbolo, signo, marca",
"节省":"ahorrar, economizar",
"研究生":"estudiante de posgrado, posgraduado",
"围巾":"bufanda, chal",
"宁静":"tranquilo, sereno, apacible; quietud",
"树林":"bosque, arboleda",
"以内":"dentro de, en menos de, sin exceder",
"多种":"múltiple, diverso, de varios tipos",
"型号":"modelo (número de), tipo, especificación",
"快递":"mensajería, paquetería, envío exprés",
"新型":"de nuevo tipo, novedoso, moderno",
"酸奶":"yogur",
"优美":"grácil, hermoso, elegante",
"耳机":"audífonos, auriculares",
"两边":"ambos lados, los dos lados",
"按时":"a tiempo, puntualmente, según lo previsto",
"分布":"distribuirse, repartirse; distribución",
"暑假":"vacaciones de verano",
"梦见":"soñar con, ver en sueños",
"高尚":"noble, elevado, digno",
"夏季":"verano, temporada estival",
"获奖":"ganar un premio, ser premiado",
"种植":"cultivar, plantar, sembrar",
"咸":"salado",
"台阶":"escalón, peldaño; salida airosa (fig.)",
"促使":"impulsar a, inducir a, llevar a",
"爱国":"patriota, patriótico; amar a la patria",
"辩论":"debatir, discutir; debate",
"种类":"tipo, clase, variedad, especie",
"默默":"en silencio, calladamente, sin decir palabra",
"未必":"no necesariamente, quizá no, no forzosamente",
"个体":"individuo; individual; por cuenta propia",
"圆满":"satisfactorio, exitoso, redondo (resultado)",
"大方":"generoso, espléndido; natural, desenvuelto; elegante",
"奖学金":"beca (de estudios)",
"泪水":"lágrimas",
"英勇":"heroico, valiente, intrépido",
"加油站":"gasolinera, estación de servicio",
"步行":"ir a pie, caminar",
"热心":"entusiasta, servicial, dedicado",
"纷纷":"uno tras otro, en masa, sucesivamente",
"流传":"difundirse, transmitirse, circular",
"简历":"currículum, CV, hoja de vida",
"专心":"concentrarse; concentrado, atento",
"使劲":"hacer fuerza, esforzarse, con ganas",
"中奖":"ganar (la lotería, un sorteo)",
"中介":"intermediario, agencia (inmobiliaria)",
"看望":"visitar, ir a ver (a alguien)",
"征求":"solicitar, pedir (opiniones)",
"实用":"práctico, útil, funcional",
"赏":"premiar, recompensar; admirar, contemplar",
"巴士":"autobús, bus",
"引进":"introducir (del exterior), importar, incorporar",
"列入":"incluir en (una lista), incorporar a",
"排列":"ordenar, alinear, disponer; permutación",
"充电":"cargar (una batería); (fig.) reciclarse, actualizarse",
"迫切":"urgente, apremiante, acuciante",
"用途":"uso, utilidad, aplicación",
"分为":"dividirse en, dividir en",
"难免":"inevitable, difícil de evitar",
"促销":"promocionar (ventas); promoción, oferta",
"体检":"examen médico, chequeo, revisión médica",
"称赞":"elogiar, alabar, felicitar",
"宝石":"piedra preciosa, gema",
"着火":"incendiarse, prenderse fuego",
"新郎":"novio (en la boda)",
"积累":"acumular; acumulación",
"光临":"honrar con su presencia, visitar (fórmula de cortesía)",
"逐步":"paso a paso, gradualmente, progresivamente",
"常识":"sentido común; conocimientos generales",
"可见":"como se ve, de esto se deduce; visible",
"食堂":"comedor, cantina, cafetería",
"晚点":"con retraso, demorado (transporte)",
"研制":"desarrollar, investigar y fabricar",
"转动":"girar, rotar, dar vueltas",
"格外":"especialmente, particularmente, sobremanera",
"离不开":"no poder prescindir de, no poder separarse de",
"列为":"clasificarse como, ser catalogado como",
"讲座":"conferencia, charla, ciclo de conferencias",
"海水":"agua de mar",
"动摇":"vacilar, titubear; tambalear(se); hacer flaquear",
"体操":"gimnasia",
"大爷":"tío (mayor); señor mayor, abuelo (trato)",
"秋季":"otoño",
"零食":"botana, golosinas, aperitivos, snacks",
"盘子":"plato, bandeja",
"表扬":"elogiar, felicitar, reconocer (méritos)",
"扩展":"expandir, extender; expansión",
"西瓜":"sandía",
"痛快":"a gusto, con gusto; directo, franco; placentero",
"平稳":"estable, firme; suave, sin sobresaltos",
"家务":"quehaceres domésticos, tareas del hogar",
"海鲜":"mariscos",
"一般来说":"en general, por lo general, generalmente",
"描写":"describir, retratar; descripción",
"相片":"fotografía, retrato",
"闹钟":"despertador",
"大姐":"hermana mayor; señora (trato respetuoso)",
"缩短":"acortar, abreviar, reducir",
"气球":"globo",
"春季":"primavera",
"长途":"larga distancia; interurbano",
"赞赏":"admirar, apreciar, elogiar",
"议论":"comentar, opinar; comentarios, habladurías",
"熟练":"hábil, experto, diestro, con soltura",
"及格":"aprobar (un examen), pasar",
"讲究":"ser exigente con, cuidar (los detalles); esmerado; refinamiento",
"构造":"estructura, constitución, construcción",
"虫子":"insecto, bicho, gusano",
"发票":"factura, recibo, comprobante",
"词汇":"vocabulario, léxico",
"不要紧":"no importa, no es grave, no pasa nada",
"刷牙":"cepillarse los dientes, lavarse los dientes",
"一再":"una y otra vez, reiteradamente",
"培育":"cultivar, criar; formar (talentos)",
"导游":"guía de turistas; guiar (un tour)",
"轮椅":"silla de ruedas",
"小吃":"antojitos, botanas, aperitivos, comida ligera",
"叶子":"hoja (de planta)",
"打折":"hacer descuento, rebajar",
"改正":"corregir, enmendar, rectificar",
"特价":"precio especial, oferta, rebaja",
"鲜明":"nítido, claro; marcado, definido; vivo (color)",
"延期":"aplazar, posponer, prorrogar",
"爱护":"cuidar, proteger con cariño, mimar",
"黄瓜":"pepino",
"堵车":"embotellamiento, atasco, tráfico congestionado",
"暖气":"calefacción; aire caliente",
"二手":"de segunda mano, usado",
"味儿":"sabor; olor",
"优良":"excelente, de primera, superior",
"转弯":"dar vuelta, girar, doblar (la esquina)",
"期末":"final del semestre, fin de curso",
"方针":"directriz, lineamiento, política",
"动画片":"película de animación, dibujos animados",
"操场":"patio (de deportes), cancha, campo de ejercicios",
"上楼":"subir (las escaleras, al piso de arriba)",
"细致":"minucioso, meticuloso, esmerado; fino",
"下楼":"bajar (las escaleras, al piso de abajo)",
"百货":"mercancías generales; (tienda) departamental",
"点名":"pasar lista; mencionar por nombre",
"陆地":"tierra firme, tierra (continental)",
"交际":"trato social, relaciones sociales; socializar",
"茶叶":"té, hojas de té",
"感兴趣":"interesarse por, tener interés en",
"邮局":"oficina de correos, correo",
"运动会":"competencia deportiva, juegos deportivos, olimpiada escolar",
"开花":"florecer, dar flor",
"登山":"escalar montañas, alpinismo, montañismo",
"潮湿":"húmedo, mojado",
"降温":"bajar la temperatura, refrescar; enfriarse (interés)",
"抽奖":"sortear, rifar; sorteo, rifa",
"概括":"resumir, sintetizar; en resumen; generalizar",
"孙女":"nieta (hija del hijo)",
"大巴":"autobús (grande), camión foráneo",
"树叶":"hojas (de árbol)",
"倒闭":"quebrar, cerrar (un negocio), irse a la bancarrota",
"坚固":"sólido, firme, resistente",
"高价":"precio alto, precio elevado",
"塑料袋":"bolsa de plástico",
"大妈":"tía; señora (mayor)",
"随手":"de paso, al pasar; sin pensarlo (cerrar la puerta, etc.)",
"转告":"transmitir (un mensaje), avisar de parte de otro",
"调皮":"travieso, pícaro, juguetón",
"公元":"era común, después de Cristo (d. C.)",
"套餐":"menú del día, combo, paquete (de servicios)",
"制订":"elaborar, formular, trazar (un plan)",
"陆续":"sucesivamente, uno tras otro, poco a poco",
"率先":"ser el primero en, tomar la delantera",
"试卷":"examen (hoja), cuadernillo de examen",
"冰雪":"hielo y nieve",
"牙刷":"cepillo de dientes",
"单调":"monótono, aburrido, uniforme",
"养成":"adquirir, formar (un hábito), cultivar",
"矿泉水":"agua mineral",
"打针":"poner una inyección, inyectar(se)",
"诚信":"honestidad, integridad; de buena fe",
"窗子":"ventana",
"再三":"una y otra vez, repetidamente, reiteradamente",
"平方":"cuadrado (metro cuadrado, etc.); al cuadrado",
"语法":"gramática",
"果实":"fruto; frutos, resultados (fig.)",
"日历":"calendario",
"月底":"fin de mes",
"内科":"medicina interna",
"深厚":"profundo, hondo (afecto); sólido (base)",
"一律":"sin excepción, uniformemente, todos por igual",
"降价":"bajar el precio, rebajar, abaratar",
"通知书":"notificación (escrita), carta de aviso",
"学问":"conocimiento, saber, erudición",
"光盘":"disco compacto, CD, DVD",
"外交官":"diplomático",
"看不起":"despreciar, menospreciar, mirar por encima del hombro",
"培训班":"curso de capacitación, taller de formación",
"外汇":"divisas, moneda extranjera",
"轮子":"rueda",
"汽水":"refresco, gaseosa, soda",
"学分":"crédito (académico)",
"能干":"capaz, competente, hábil",
"风俗":"costumbre, usanza, tradición",
"摆动":"oscilar, balancearse, mecerse",
"开水":"agua hervida, agua hirviendo",
"充电器":"cargador (de batería)",
"红包":"sobre rojo (con dinero de regalo); bono; propina",
"倒车":"dar marcha atrás, ir en reversa; hacer transbordo",
"后头":"detrás, atrás; después",
"片面":"unilateral, parcial, sesgado",
"本科":"licenciatura, pregrado",
"轮船":"barco de vapor, buque",
"宽广":"amplio, vasto, extenso",
"前头":"delante, al frente, adelante",
"汇率":"tipo de cambio, tasa de cambio",
"急忙":"apresuradamente, a toda prisa, deprisa",
"期中":"mitad del semestre, parcial (examen)",
"网址":"dirección web, URL, sitio",
"吸管":"popote, pajilla, sorbete",
"窗台":"alféizar, repisa de la ventana",
"松树":"pino",
"多样":"variado, diverso; diversidad",
"学年":"año escolar, año académico",
"售货员":"vendedor, dependiente",
"电灯":"luz eléctrica, lámpara, foco",
"口语":"lengua hablada, expresión oral, coloquial",
"近代":"época moderna, edad contemporánea (en historia china: 1840-1919)",
"疗养":"convalecer, reposar, recuperarse",
"寒假":"vacaciones de invierno",
"矮小":"pequeño y bajo, menudo",
"粗心":"descuidado, distraído, negligente",
"刷子":"cepillo, brocha",
"毫米":"milímetro",
"厘米":"centímetro",
"亚运会":"Juegos Asiáticos",
"高铁":"tren de alta velocidad",
"电动车":"vehículo eléctrico, moto eléctrica",
"毫升":"mililitro",
"打雷":"tronar; trueno",
"五颜六色":"multicolor, de todos los colores, colorido",
"隔开":"separar, dividir, apartar",
"模特儿":"modelo (de moda)",
"抄写":"copiar, transcribir",
"括号":"paréntesis, corchetes",
"尺子":"regla (para medir)",
"没法儿":"no haber manera, imposible",
"纯净水":"agua purificada",
"分之":"(indica fracción: 三分之一 = un tercio)",
"填空":"rellenar espacios (en un examen); cubrir una vacante",
"学时":"hora de clase, hora lectiva",
"没想到":"no imaginarse, no esperarse, quién iba a pensar",
"名牌儿":"marca famosa, de marca",
"微信":"WeChat (aplicación de mensajería)",
"下个月":"el próximo mes",
"有劲儿":"tener fuerza, con energía, vigoroso"
}
